{
  "id": "fc0262f4-336a-4cf0-adc1-12aa911f13ab",
  "title": "Forcer la synchronisation d\u0027un client avec WSUS",
  "description": "Force le client Windows Update \u00E0 se synchroniser imm\u00E9diatement avec le serveur WSUS",
  "category": "\uD83D\uDD04 Windows Updates",
  "platform": "Windows",
  "level": "Info",
  "tags": [
    "wsus",
    "sync",
    "client",
    "update"
  ],
  "windowsTemplateId": "0f85b67a-5aed-4ddc-bc16-926c08509b6b",
  "examples": [],
  "windowsExamples": [],
  "linuxExamples": [],
  "notes": "wuauclt est l\u0027outil classique, usoclient est recommand\u00E9 pour Windows 10/11. Le client signalera son \u00E9tat au serveur WSUS imm\u00E9diatement.",
  "links": [
    {
      "title": "WSUS Client Commands",
      "url": "https://techdirectarchive.com/2020/02/05/handy-windows-server-update-services-commands-wauaclt-powershell-and-usoclient/"
    }
  ],
  "isUserCreated": false
}