{
  "id": "7b392cf8-ff32-4ee0-82d8-30c462ef0656",
  "title": "D\u00E9sactiver Superfetch/SysMain",
  "description": "D\u00E9sactive le service Superfetch (SysMain) qui pr\u00E9charge des applications en RAM. Utile sur SSD.",
  "category": "\uD83D\uDCBB Windows Optimization",
  "platform": "Windows",
  "level": "Run",
  "tags": [
    "performance",
    "services",
    "superfetch",
    "sysmain",
    "ssd",
    "optimisation",
    "windows"
  ],
  "examples": [],
  "windowsExamples": [],
  "linuxExamples": [],
  "notes": "Superfetch (SysMain): pr\u00E9charge les applications fr\u00E9quemment utilis\u00E9es en RAM. Utile sur HDD, contre-productif sur SSD (les SSD sont d\u00E9j\u00E0 rapides). D\u00E9sactiver sur SSD lib\u00E8re RAM et r\u00E9duit les \u00E9critures disque. Garder actif sur HDD.",
  "links": [],
  "isUserCreated": false
}